hydrocomp/__init__.py
hydrocomp/api_ana/__init__.py
hydrocomp/api_ana/api_biuld.py
hydrocomp/api_ana/basin.py
hydrocomp/api_ana/inventario.py
hydrocomp/api_ana/serie_temporal.py
hydrocomp/comparasion/__init__.py
hydrocomp/comparasion/bootstrap_build.py
hydrocomp/comparasion/genpareto.py
hydrocomp/comparasion/mae.py
hydrocomp/comparasion/quantify_uncertainty.py
hydrocomp/comparasion/rmae.py
hydrocomp/comparasion/rmse.py
hydrocomp/files/__init__.py
hydrocomp/files/ana.py
hydrocomp/files/cemaden.py
hydrocomp/files/chesf.py
hydrocomp/files/fileRead.py
hydrocomp/files/fileWrite.py
hydrocomp/files/files.py
hydrocomp/files/nasa.py
hydrocomp/files/ons.py
hydrocomp/files/semarh.py
hydrocomp/graphics/__init__.py
hydrocomp/graphics/boxplot.py
hydrocomp/graphics/comparationdistribution.py
hydrocomp/graphics/distribution_biuld.py
hydrocomp/graphics/gantt.py
hydrocomp/graphics/genextreme.py
hydrocomp/graphics/genpareto.py
hydrocomp/graphics/hydrogram_annual.py
hydrocomp/graphics/hydrogram_build.py
hydrocomp/graphics/hydrogram_by_year.py
hydrocomp/graphics/hydrogram_clean.py
hydrocomp/graphics/hydrogram_parcial.py
hydrocomp/graphics/permanence_curve.py
hydrocomp/graphics/.ipynb_checkpoints/__init__.py
hydrocomp/graphics/.ipynb_checkpoints/gantt-checkpoint.py
hydrocomp/graphics/.ipynb_checkpoints/hydrogram_annual-checkpoint.py
hydrocomp/graphics/.ipynb_checkpoints/hydrogram_biuld-checkpoint.py
hydrocomp/graphics/.ipynb_checkpoints/hydrogram_clean-checkpoint.py
hydrocomp/graphics/.ipynb_checkpoints/hydrogram_parcial-checkpoint.py
hydrocomp/iha/__init__.py
hydrocomp/iha/exceptions.py
hydrocomp/iha/graphics.py
hydrocomp/iha/iha.py
hydrocomp/series/__init__.py
hydrocomp/series/exceptions.py
hydrocomp/series/flow.py
hydrocomp/series/height.py
hydrocomp/series/maximum.py
hydrocomp/series/parcial.py
hydrocomp/series/rainfall.py
hydrocomp/series/series_build.py
hydrocomp/statistic/__init__.py
hydrocomp/statistic/exceptions.py
hydrocomp/statistic/genextre.py
hydrocomp-0.1.4.dist-info/METADATA
hydrocomp-0.1.4.dist-info/WHEEL
hydrocomp-0.1.4.dist-info/top_level.txt
hydrocomp-0.1.4.dist-info/RECORD
